test/__init__.py
test/test.py
unetpy/__init__.py
unetpy-3.1.3.dist-info/licenses/LICENSE
unetpy-3.1.3.dist-info/METADATA
unetpy-3.1.3.dist-info/WHEEL
unetpy-3.1.3.dist-info/top_level.txt
unetpy-3.1.3.dist-info/RECORD
