Metadata-Version: 2.4
Name: unetpy
Version: 3.1.3
Summary: Unet Python Gateway
Home-page: https://github.com/org-arl/unet-contrib/tree/master/unetsocket/python
Author: Mandar Chitre, Prasad Anjangi
Author-email: mandar@arl.nus.edu.sg, prasad@subnero.com
License: BSD (3-clause)
Classifier: Development Status :: 5 - Production/Stable
Classifier: Programming Language :: Python :: 3.5
Classifier: Programming Language :: Python :: 3.6
Classifier: Programming Language :: Python :: 3.7
Classifier: Programming Language :: Python :: 3.8
Classifier: Programming Language :: Python :: 3.9
Classifier: Programming Language :: Python :: 3.10
Requires-Python: >=3
License-File: LICENSE
Requires-Dist: numpy>=1.11
Requires-Dist: fjagepy<2,>=1.7.2
Dynamic: author
Dynamic: author-email
Dynamic: classifier
Dynamic: description
Dynamic: description-content-type
Dynamic: home-page
Dynamic: license
Dynamic: license-file
Dynamic: requires-dist
Dynamic: requires-python
Dynamic: summary
